ffmpeg_cut/__init__.py
ffmpeg_cut/__main__.py
ffmpeg_cut/cli.py
ffmpeg_cut/structs.py
ffmpeg_cut-1.0.2.dist-info/AUTHORS.rst
ffmpeg_cut-1.0.2.dist-info/LICENSE
ffmpeg_cut-1.0.2.dist-info/METADATA
ffmpeg_cut-1.0.2.dist-info/WHEEL
ffmpeg_cut-1.0.2.dist-info/entry_points.txt
ffmpeg_cut-1.0.2.dist-info/top_level.txt
ffmpeg_cut-1.0.2.dist-info/RECORD
